swarmauri_tokens_rotatingjwt/__init__.py
swarmauri_tokens_rotatingjwt/rotating_jwt.py
swarmauri_tokens_rotatingjwt-0.3.0.dev5.dist-info/LICENSE
swarmauri_tokens_rotatingjwt-0.3.0.dev5.dist-info/METADATA
swarmauri_tokens_rotatingjwt-0.3.0.dev5.dist-info/WHEEL
swarmauri_tokens_rotatingjwt-0.3.0.dev5.dist-info/entry_points.txt
swarmauri_tokens_rotatingjwt-0.3.0.dev5.dist-info/RECORD
